[{"image": "11.jpg", "verified": false, "annotations": [{"label": "player", "coordinates": {"x": 1795.921052631579, "y": 380.8947368421052, "width": 68.0, "height": 108.0}}, {"label": "player", "coordinates": {"x": 1373.921052631579, "y": 1020.9473684210526, "width": 90.0, "height": 118.1052631578948}}, {"label": "player", "coordinates": {"x": 1367.921052631579, "y": 577.8947368421052, "width": 60.0, "height": 134.0}}, {"label": "player", "coordinates": {"x": 921.421052631579, "y": 635.3947368421052, "width": 61.0, "height": 157.0}}, {"label": "player", "coordinates": {"x": 1171.921052631579, "y": 462.3947368421052, "width": 62.0, "height": 119.0}}, {"label": "player", "coordinates": {"x": 999.921052631579, "y": 448.3947368421052, "width": 74.0, "height": 115.0}}, {"label": "player", "coordinates": {"x": 1026.921052631579, "y": 313.8947368421052, "width": 56.0, "height": 92.0}}, {"label": "player", "coordinates": {"x": 1253.421052631579, "y": 263.3947368421052, "width": 49.0, "height": 102.99999999999997}}, {"label": "player", "coordinates": {"x": 486.42105263157896, "y": 505.3947368421052, "width": 77.0, "height": 129.0}}, {"label": "player", "coordinates": {"x": 123.42105263157899, "y": 678.8947368421052, "width": 87.00000000000001, "height": 152.0}}, {"label": "player", "coordinates": {"x": 402.92105263157896, "y": 953.8947368421052, "width": 98.0, "height": 178.0}}, {"label": "player", "coordinates": {"x": 39.96052631578949, "y": 806.3947368421052, "width": 79.92105263157897, "height": 149.0}}, {"label": "ball", "coordinates": {"x": 1133.5, "y": 280.9397590361446, "width": 21.0, "height": 24.0}}]}]